commandbus/__init__.py
commandbus/batch.py
commandbus/bus.py
commandbus/exceptions.py
commandbus/handler.py
commandbus/models.py
commandbus/policies.py
commandbus/setup.py
commandbus/worker.py
commandbus/_core/__init__.py
commandbus/_core/batch_sql.py
commandbus/_core/command_sql.py
commandbus/_core/pgmq_sql.py
commandbus/_core/process_sql.py
commandbus/migrations/V002__add_failed_count.sql
commandbus/migrations/__init__.py
commandbus/ops/__init__.py
commandbus/ops/troubleshooting.py
commandbus/pgmq/__init__.py
commandbus/pgmq/client.py
commandbus/process/__init__.py
commandbus/process/base.py
commandbus/process/models.py
commandbus/process/repository.py
commandbus/process/router.py
commandbus/repositories/__init__.py
commandbus/repositories/audit.py
commandbus/repositories/batch.py
commandbus/repositories/command.py
commandbus/sync/__init__.py
commandbus/sync/bus.py
commandbus/sync/health.py
commandbus/sync/pgmq.py
commandbus/sync/timeouts.py
commandbus/sync/watchdog.py
commandbus/sync/worker.py
commandbus/sync/process/__init__.py
commandbus/sync/process/router.py
commandbus/sync/repositories/__init__.py
commandbus/sync/repositories/audit.py
commandbus/sync/repositories/batch.py
commandbus/sync/repositories/command.py
commandbus/sync/repositories/process.py
commandbus/testing/__init__.py
commandbus/migrations/V001__commandbus_schema.sql
reliable_cmd-0.2.2.dist-info/METADATA
reliable_cmd-0.2.2.dist-info/WHEEL
reliable_cmd-0.2.2.dist-info/RECORD
