Metadata-Version: 2.4
Name: reliable-cmd
Version: 0.2.2
Summary: Command Bus abstraction over PostgreSQL + PGMQ for reliable async command processing
Project-URL: Homepage, https://github.com/FreeSideNomad/rcmd
Project-URL: Documentation, https://github.com/FreeSideNomad/rcmd#readme
Project-URL: Repository, https://github.com/FreeSideNomad/rcmd
Project-URL: Issues, https://github.com/FreeSideNomad/rcmd/issues
Project-URL: Changelog, https://github.com/FreeSideNomad/rcmd/releases
Author: FreeSideNomad
License-Expression: MIT
Keywords: async,command-bus,commandbus,cqrs,message-queue,pgmq,postgresql
Classifier: Development Status :: 4 - Beta
Classifier: Framework :: AsyncIO
Classifier: Intended Audience :: Developers
Classifier: License :: OSI Approved :: MIT License
Classifier: Operating System :: OS Independent
Classifier: Programming Language :: Python :: 3
Classifier: Programming Language :: Python :: 3.11
Classifier: Programming Language :: Python :: 3.12
Classifier: Programming Language :: Python :: 3.13
Classifier: Topic :: Database
Classifier: Topic :: Software Development :: Libraries :: Python Modules
Classifier: Typing :: Typed
Requires-Python: >=3.11
Requires-Dist: orjson>=3.10.0
Requires-Dist: psycopg[binary,pool]>=3.2.0
Provides-Extra: dev
Requires-Dist: mypy>=1.13.0; extra == 'dev'
Requires-Dist: pre-commit>=4.0.0; extra == 'dev'
Requires-Dist: pytest-asyncio>=0.24.0; extra == 'dev'
Requires-Dist: pytest-cov>=6.0.0; extra == 'dev'
Requires-Dist: pytest>=8.0.0; extra == 'dev'
Requires-Dist: ruff>=0.8.0; extra == 'dev'
Provides-Extra: e2e
Requires-Dist: fastapi>=0.128.0; extra == 'e2e'
Requires-Dist: jinja2>=3.1.6; extra == 'e2e'
Requires-Dist: python-dotenv>=1.0.1; extra == 'e2e'
Requires-Dist: python-multipart>=0.0.20; extra == 'e2e'
Requires-Dist: uvicorn[standard]>=0.40.0; extra == 'e2e'
Provides-Extra: test
Requires-Dist: pytest-asyncio>=0.24.0; extra == 'test'
Requires-Dist: pytest-cov>=6.0.0; extra == 'test'
Requires-Dist: pytest>=8.0.0; extra == 'test'
Requires-Dist: testcontainers[postgres]>=4.0.0; extra == 'test'
